nk30.py
nk30-1.0.3.dist-info/licenses/LICENSE
nk30-1.0.3.dist-info/METADATA
nk30-1.0.3.dist-info/WHEEL
nk30-1.0.3.dist-info/top_level.txt
nk30-1.0.3.dist-info/RECORD
